richer/__init__.py
richer/console.py
richer/interactive_console.py
richer/parser.py
richer/table.py
richer/text.py
richer-0.1.6.dist-info/LICENSE
richer-0.1.6.dist-info/METADATA
richer-0.1.6.dist-info/WHEEL
richer-0.1.6.dist-info/top_level.txt
richer-0.1.6.dist-info/RECORD
